pytorrentz/__init__.py
pytorrentz/exceptions.py
pytorrentz/torrentz.py
pytorrentz-0.1.7.dist-info/DESCRIPTION.rst
pytorrentz-0.1.7.dist-info/METADATA
pytorrentz-0.1.7.dist-info/RECORD
pytorrentz-0.1.7.dist-info/WHEEL
pytorrentz-0.1.7.dist-info/metadata.json
pytorrentz-0.1.7.dist-info/top_level.txt
