Metadata-Version: 2.0
Name: pytorrentz
Version: 0.1.7
Summary: Python interface to https://www.torrentz.eu -- based on https://github.com/dannvix/torrentz-magdl
Home-page: https://github.com/srob650/pytorrentz
Author: srob650
Author-email: pytvmaze@gmail.com
License: MIT
Keywords: python torrentz torrents torrent
Platform: UNKNOWN
Classifier: Development Status :: 2 - Pre-Alpha
Classifier: Intended Audience :: Developers
Classifier: License :: OSI Approved :: MIT License
Classifier: Programming Language :: Python :: 2.7
Classifier: Programming Language :: Python :: 3.5
Requires-Dist: requests
Requires-Dist: bs4
Requires-Dist: cfscrape
